setup.py
mozautolog/__init__.py
mozautolog/buildlog.py
mozautolog/esautolog.py
mozautolog/mozautolog.py
mozautolog.egg-info/PKG-INFO
mozautolog.egg-info/SOURCES.txt
mozautolog.egg-info/dependency_links.txt
mozautolog.egg-info/not-zip-safe
mozautolog.egg-info/requires.txt
mozautolog.egg-info/top_level.txt