Metadata-Version: 1.0
Name: mozautolog
Version: 0.2.2
Summary: Library for posting results to Autolog via HTTP POST
Home-page: http://hg.mozilla.org/automation/mozautolog
Author: Jonathan Griffin
Author-email: jgriffin@mozilla.com
License: MPL
Platform: UNKNOWN
